tickcatcher/__init__.py
tickcatcher/api_client.py
tickcatcher/api_response.py
tickcatcher/configuration.py
tickcatcher/exceptions.py
tickcatcher/py.typed
tickcatcher/rest.py
tickcatcher/api/__init__.py
tickcatcher/api/calendar_api.py
tickcatcher/api/candles_api.py
tickcatcher/api/general_api.py
tickcatcher/api/indicators_api.py
tickcatcher/models/__init__.py
tickcatcher/models/adx200_response_inner.py
tickcatcher/models/adx_request.py
tickcatcher/models/atr_request.py
tickcatcher/models/bbands200_response_inner.py
tickcatcher/models/bbands_request.py
tickcatcher/models/bbands_request_params.py
tickcatcher/models/calendar_event.py
tickcatcher/models/candle.py
tickcatcher/models/cci_request.py
tickcatcher/models/ema_request.py
tickcatcher/models/ema_request_params.py
tickcatcher/models/heikenashi_request.py
tickcatcher/models/ichimoku200_response_inner.py
tickcatcher/models/ichimoku_request.py
tickcatcher/models/ichimoku_request_params.py
tickcatcher/models/info.py
tickcatcher/models/keltner_request.py
tickcatcher/models/keltner_request_params.py
tickcatcher/models/macd200_response_inner.py
tickcatcher/models/macd_request.py
tickcatcher/models/macd_request_params.py
tickcatcher/models/metadata.py
tickcatcher/models/pivot200_response_inner.py
tickcatcher/models/pivot_request.py
tickcatcher/models/psar_request.py
tickcatcher/models/psar_request_params.py
tickcatcher/models/rsi_request.py
tickcatcher/models/search_result.py
tickcatcher/models/sma_request.py
tickcatcher/models/sma_request_params.py
tickcatcher/models/stoch200_response_inner.py
tickcatcher/models/stoch_request.py
tickcatcher/models/stoch_request_params.py
tickcatcher/models/supertrend200_response_inner.py
tickcatcher/models/supertrend_request.py
tickcatcher/models/supertrend_request_params.py
tickcatcher/models/volumema_request.py
tickcatcher/models/vwap_request.py
tickcatcher/models/williamsr_request.py
tickcatcher/models/zigzag_request.py
tickcatcher/models/zigzag_request_params.py
tickcatcher-1.1.7.dist-info/METADATA
tickcatcher-1.1.7.dist-info/WHEEL
tickcatcher-1.1.7.dist-info/top_level.txt
tickcatcher-1.1.7.dist-info/RECORD
