Metadata-Version: 2.4
Name: tickcatcher
Version: 1.1.7
Summary: Tickcatcher API
Home-page: https://github.com/yagiziskirik/tickcatcher-sdk
Author: OpenAPI Generator community
Author-email: OpenAPI Generator Community <yagiz@iskirik.com>
License: MIT
Project-URL: Repository, https://github.com/yagiziskirik/tickcatcher-sdk
Keywords: OpenAPI,OpenAPI-Generator,Tickcatcher API
Requires-Python: >=3.9
Requires-Dist: urllib3<3.0.0,>=2.1.0
Requires-Dist: python-dateutil>=2.8.2
Requires-Dist: pydantic>=2
Requires-Dist: typing-extensions>=4.7.1
Dynamic: author
Dynamic: home-page
